strain/__init__.py
strain/_strain.py
strain/_version.py
strain/parameter.py
strain/structure/__init__.py
strain/structure/three_five.py
strain-0.1.0.dist-info/METADATA
strain-0.1.0.dist-info/RECORD
strain-0.1.0.dist-info/WHEEL
strain-0.1.0.dist-info/top_level.txt
