Metadata-Version: 2.1
Name: strain
Version: 0.1.0
Summary: UNKNOWN
Home-page: UNKNOWN
Author: Dominik Gresch
Author-email: greschd@gmx.ch
License: GPL
Platform: UNKNOWN
Classifier: License :: OSI Approved :: GNU General Public License v3 (GPLv3)
Classifier: Natural Language :: English
Classifier: Operating System :: Unix
Classifier: Development Status :: 3 - Alpha
Classifier: Programming Language :: Python
Classifier: Programming Language :: Python :: 2.7
Classifier: Programming Language :: Python :: 3.4
Classifier: Programming Language :: Python :: 3.5
Classifier: Programming Language :: Python :: 3.6
Classifier: Intended Audience :: Science/Research
Classifier: Topic :: Scientific/Engineering :: Physics
Provides-Extra: dev
Requires-Dist: numpy
Requires-Dist: pymatgen
Requires-Dist: fsc.export
Provides-Extra: dev
Requires-Dist: pytest; extra == 'dev'
Requires-Dist: pre-commit; extra == 'dev'
Requires-Dist: yapf (==0.21.0); extra == 'dev'
Requires-Dist: prospector; extra == 'dev'
Requires-Dist: sphinx; extra == 'dev'
Requires-Dist: sphinx-rtd-theme (<0.3); extra == 'dev'
